tests/__init__.py
tests/test_enforce_types.py
tests/test_exceptions.py
type_enforcer/__init__.py
type_enforcer/exceptions.py
type_enforcer/main.py
static_type_enforcer-0.1.0.dist-info/LICENSE
static_type_enforcer-0.1.0.dist-info/METADATA
static_type_enforcer-0.1.0.dist-info/WHEEL
static_type_enforcer-0.1.0.dist-info/top_level.txt
static_type_enforcer-0.1.0.dist-info/RECORD
