Metadata-Version: 2.1
Name: static_type_enforcer
Version: 0.1.0
Summary: A lightweight decorator for enforcing type hints at runtime.
Home-page: https://github.com/WazedKhan/enforcer
Author: Wajed Khan
Author-email: Wajed Khan <wajed.abdul.khan@gmail.com>
License: MIT
Project-URL: Home, https://github.com/WazedKhan/enforcer
Classifier: Programming Language :: Python :: 3
Classifier: License :: OSI Approved :: MIT License
Classifier: Operating System :: OS Independent
Requires-Python: >=3.7
License-File: LICENSE
